odoo/addons/stock_picking_package_grouped/README.rst
odoo/addons/stock_picking_package_grouped/__init__.py
odoo/addons/stock_picking_package_grouped/__manifest__.py
odoo/addons/stock_picking_package_grouped/i18n/es.po
odoo/addons/stock_picking_package_grouped/i18n/stock_picking_package_grouped.pot
odoo/addons/stock_picking_package_grouped/models/__init__.py
odoo/addons/stock_picking_package_grouped/models/stock_picking.py
odoo/addons/stock_picking_package_grouped/models/stock_picking_type.py
odoo/addons/stock_picking_package_grouped/readme/CONFIGURE.rst
odoo/addons/stock_picking_package_grouped/readme/CONTRIBUTORS.rst
odoo/addons/stock_picking_package_grouped/readme/DESCRIPTION.rst
odoo/addons/stock_picking_package_grouped/readme/USAGE.rst
odoo/addons/stock_picking_package_grouped/static/description/icon.png
odoo/addons/stock_picking_package_grouped/static/description/index.html
odoo/addons/stock_picking_package_grouped/tests/__init__.py
odoo/addons/stock_picking_package_grouped/tests/test_stock_picking_package_grouped.py
odoo/addons/stock_picking_package_grouped/views/stock_picking_type_views.xml
odoo13_addon_stock_picking_package_grouped-13.0.1.0.2.dev2.dist-info/METADATA
odoo13_addon_stock_picking_package_grouped-13.0.1.0.2.dev2.dist-info/WHEEL
odoo13_addon_stock_picking_package_grouped-13.0.1.0.2.dev2.dist-info/top_level.txt
odoo13_addon_stock_picking_package_grouped-13.0.1.0.2.dev2.dist-info/RECORD
